rok4_tools/__init__.py
rok4_tools/joincache.py
rok4_tools/make_layer.py
rok4_tools/pyr2pyr.py
rok4_tools/pyrolyse.py
rok4_tools/tmsizer.py
rok4_tools/global_utils/source.py
rok4_tools/joincache_utils/agent.py
rok4_tools/joincache_utils/example.json
rok4_tools/joincache_utils/finisher.py
rok4_tools/joincache_utils/master.py
rok4_tools/joincache_utils/schema.json
rok4_tools/pyr2pyr_utils/__init__.py
rok4_tools/pyr2pyr_utils/agent.py
rok4_tools/pyr2pyr_utils/example.json
rok4_tools/pyr2pyr_utils/finisher.py
rok4_tools/pyr2pyr_utils/master.py
rok4_tools/pyr2pyr_utils/schema.json
rok4_tools/tmsizer_utils/processors/__init__.py
rok4_tools/tmsizer_utils/processors/io.py
rok4_tools/tmsizer_utils/processors/map.py
rok4_tools/tmsizer_utils/processors/processor.py
rok4_tools/tmsizer_utils/processors/reduce.py
rok4_tools-1.5.2.dist-info/LICENSE.txt
rok4_tools-1.5.2.dist-info/METADATA
rok4_tools-1.5.2.dist-info/WHEEL
rok4_tools-1.5.2.dist-info/entry_points.txt
rok4_tools-1.5.2.dist-info/top_level.txt
rok4_tools-1.5.2.dist-info/RECORD
