Metadata-Version: 2.1
Name: rok4-tools
Version: 1.5.2
Summary: Python tools for ROK4 project
Author-email: Géoportail Developer <tout_rdev@ign.fr>
License: 
Project-URL: Homepage, https://rok4.github.io/pytools
Project-URL: Bug Reports, https://github.com/rok4/pytools/issues
Project-URL: Changelog, https://rok4.github.io/pytools/latest/CHANGELOG/
Project-URL: Source, https://github.com/rok4/pytools
Keywords: ROK4,tools,data pyramids
Classifier: Development Status :: 3 - Alpha
Classifier: Topic :: Software Development :: Build Tools
Classifier: License :: CeCILL-C Free Software License Agreement (CECILL-C)
Classifier: Programming Language :: Python :: 3
Classifier: Programming Language :: Python :: 3.8
Classifier: Programming Language :: Python :: 3.9
Classifier: Programming Language :: Python :: 3.10
Classifier: Programming Language :: Python :: 3.11
Classifier: Programming Language :: Python :: 3 :: Only
Requires-Python: >=3.8
License-File: LICENSE.txt
Requires-Dist: jsonschema
Requires-Dist: tqdm
Requires-Dist: rasterio
Requires-Dist: rok4<3.0.0,>=2.1.5
Provides-Extra: dev
Requires-Dist: black; extra == "dev"
Requires-Dist: isort>=5.12.0; extra == "dev"
Requires-Dist: pre-commit<4,>3; extra == "dev"
Requires-Dist: ruff>=0.0.281; extra == "dev"
Provides-Extra: doc
Requires-Dist: pdoc3>=0.10.0; extra == "doc"
Provides-Extra: test
Requires-Dist: pytest>=7.1.2; extra == "test"
Requires-Dist: coverage>=7.0.5; extra == "test"
